{
  "updated_at": "2026-02-05T21:58:53.631950",
  "assets": {
    "GC=F": {
      "price": 4790.0,
      "change_pct": -2.650189109255859,
      "prev_close": 4920.39990234375,
      "name": "黄金",
      "updated": "2026-02-05T21:58:54.284315",
      "unit": "USD/oz",
      "icon": "🥇",
      "category": "metals"
    },
    "SI=F": {
      "price": 70.63500213623047,
      "change_pct": -16.07556422755384,
      "prev_close": 84.16500091552734,
      "name": "白银",
      "updated": "2026-02-05T21:58:54.500178",
      "unit": "USD/oz",
      "icon": "🥈",
      "category": "metals"
    },
    "HG=F": {
      "price": 5.7170000076293945,
      "change_pct": -1.8709269137816902,
      "prev_close": 5.826000213623047,
      "name": "铜",
      "updated": "2026-02-05T21:58:54.691927",
      "unit": "USD/吨",
      "icon": "🔶",
      "category": "metals"
    },
    "NICK.L": {
      "price": 15.0,
      "change_pct": -1.7681758328068453,
      "prev_close": 15.270000457763672,
      "name": "镍",
      "updated": "2026-02-05T21:58:54.902717",
      "unit": "USD (ETC)",
      "icon": "⚙️",
      "category": "metals"
    },
    "REMX": {
      "price": 81.66000366210938,
      "change_pct": -6.20261204676698,
      "prev_close": 87.05999755859375,
      "name": "稀土ETF",
      "updated": "2026-02-05T21:58:55.174717",
      "unit": "USD",
      "icon": "💎",
      "category": "metals"
    },
    "CL=F": {
      "price": 63.130001068115234,
      "change_pct": -3.0856591040321946,
      "prev_close": 65.13999938964844,
      "name": "WTI原油",
      "updated": "2026-02-05T21:58:55.445189",
      "unit": "USD/bbl",
      "icon": "🛢️",
      "category": "commodities"
    },
    "BTCUSDT": {
      "error": true,
      "name": "BTC",
      "updated": "2026-02-05T21:58:55.702158"
    },
    "ETHUSDT": {
      "error": true,
      "name": "ETH",
      "updated": "2026-02-05T21:58:55.809051"
    },
    "CNY=X": {
      "price": 6.937300205230713,
      "change_pct": -0.005759683330136182,
      "prev_close": 6.937699794769287,
      "name": "USD/CNY",
      "updated": "2026-02-05T21:58:56.098569",
      "unit": "",
      "icon": "🇨🇳",
      "category": "fx"
    },
    "JPY=X": {
      "price": 157.0260009765625,
      "change_pct": 0.7875564262980559,
      "prev_close": 155.7989959716797,
      "name": "USD/JPY",
      "updated": "2026-02-05T21:58:56.283792",
      "unit": "",
      "icon": "🇯🇵",
      "category": "fx"
    },
    "EURUSD=X": {
      "price": 1.1782727241516113,
      "change_pct": -0.28277568308704,
      "prev_close": 1.1816140413284302,
      "name": "EUR/USD",
      "updated": "2026-02-05T21:58:56.533738",
      "unit": "",
      "icon": "🇪🇺",
      "category": "fx"
    }
  },
  "meta": {
    "total_assets": 11,
    "successful_fetches": 9,
    "failed_fetches": 2
  }
}