{
  "updated_at": "2026-03-30T12:36:03.891731",
  "assets": {
    "GC=F": {
      "price": 4593.7998046875,
      "change_pct": 2.2662467650823683,
      "prev_close": 4492.0,
      "name": "黄金",
      "updated": "2026-03-30T12:36:04.099150",
      "unit": "USD/oz",
      "icon": "🥇",
      "category": "metals"
    },
    "SI=F": {
      "price": 71.34500122070312,
      "change_pct": 2.5882566671223057,
      "prev_close": 69.54499816894531,
      "name": "白银",
      "updated": "2026-03-30T12:36:04.265841",
      "unit": "USD/oz",
      "icon": "🥈",
      "category": "metals"
    },
    "HG=F": {
      "price": 5.5229997634887695,
      "change_pct": 1.0243233177469422,
      "prev_close": 5.4670000076293945,
      "name": "铜",
      "updated": "2026-03-30T12:36:04.415240",
      "unit": "USD/吨",
      "icon": "🔶",
      "category": "metals"
    },
    "NICK.L": {
      "price": 15.164999961853027,
      "change_pct": 0.5636607332693081,
      "prev_close": 15.079999923706055,
      "name": "镍",
      "updated": "2026-03-30T12:36:04.581081",
      "unit": "USD (ETC)",
      "icon": "⚙️",
      "category": "metals"
    },
    "REMX": {
      "price": 86.0999984741211,
      "change_pct": 1.773049677369493,
      "prev_close": 84.5999984741211,
      "name": "稀土ETF",
      "updated": "2026-03-30T12:36:04.687304",
      "unit": "USD",
      "icon": "💎",
      "category": "metals"
    },
    "CL=F": {
      "price": 101.12999725341797,
      "change_pct": 1.495381245379982,
      "prev_close": 99.63999938964844,
      "name": "WTI原油",
      "updated": "2026-03-30T12:36:04.768549",
      "unit": "USD/bbl",
      "icon": "🛢️",
      "category": "commodities"
    },
    "BTCUSDT": {
      "error": true,
      "name": "BTC",
      "updated": "2026-03-30T12:36:04.944491"
    },
    "ETHUSDT": {
      "error": true,
      "name": "ETH",
      "updated": "2026-03-30T12:36:04.981757"
    },
    "CNY=X": {
      "price": 6.9105000495910645,
      "change_pct": -0.0028910931423270663,
      "prev_close": 6.910699844360352,
      "name": "USD/CNY",
      "updated": "2026-03-30T12:36:05.060554",
      "unit": "",
      "icon": "🇨🇳",
      "category": "fx"
    },
    "JPY=X": {
      "price": 159.45599365234375,
      "change_pct": -0.15528797449275827,
      "prev_close": 159.70399475097656,
      "name": "USD/JPY",
      "updated": "2026-03-30T12:36:05.270675",
      "unit": "",
      "icon": "🇯🇵",
      "category": "fx"
    },
    "EURUSD=X": {
      "price": 1.1486331224441528,
      "change_pct": -0.4227013636878012,
      "prev_close": 1.1535090208053589,
      "name": "EUR/USD",
      "updated": "2026-03-30T12:36:05.385256",
      "unit": "",
      "icon": "🇪🇺",
      "category": "fx"
    }
  },
  "meta": {
    "total_assets": 11,
    "successful_fetches": 9,
    "failed_fetches": 2
  }
}