{
  "updated_at": "2026-02-17T19:35:14.118230",
  "assets": {
    "GC=F": {
      "price": 4909.7998046875,
      "change_pct": -2.234173542662286,
      "prev_close": 5022.0,
      "name": "黄金",
      "updated": "2026-02-17T19:35:14.421627",
      "unit": "USD/oz",
      "icon": "🥇",
      "category": "metals"
    },
    "SI=F": {
      "price": 73.69999694824219,
      "change_pct": -5.331981717911825,
      "prev_close": 77.85099792480469,
      "name": "白银",
      "updated": "2026-02-17T19:35:14.524018",
      "unit": "USD/oz",
      "icon": "🥈",
      "category": "metals"
    },
    "HG=F": {
      "price": 5.684000015258789,
      "change_pct": -1.8731118421653783,
      "prev_close": 5.792500019073486,
      "name": "铜",
      "updated": "2026-02-17T19:35:14.622725",
      "unit": "USD/吨",
      "icon": "🔶",
      "category": "metals"
    },
    "NICK.L": {
      "price": 14.835000038146973,
      "change_pct": -1.3302282094772455,
      "prev_close": 15.03499984741211,
      "name": "镍",
      "updated": "2026-02-17T19:35:14.687764",
      "unit": "USD (ETC)",
      "icon": "⚙️",
      "category": "metals"
    },
    "REMX": {
      "price": 89.17500305175781,
      "change_pct": -0.5852774964834189,
      "prev_close": 89.69999694824219,
      "name": "稀土ETF",
      "updated": "2026-02-17T19:35:14.798215",
      "unit": "USD",
      "icon": "💎",
      "category": "metals"
    },
    "CL=F": {
      "price": 62.369998931884766,
      "change_pct": -0.8268412510896969,
      "prev_close": 62.88999938964844,
      "name": "WTI原油",
      "updated": "2026-02-17T19:35:14.862428",
      "unit": "USD/bbl",
      "icon": "🛢️",
      "category": "commodities"
    },
    "BTCUSDT": {
      "error": true,
      "name": "BTC",
      "updated": "2026-02-17T19:35:15.058312"
    },
    "ETHUSDT": {
      "error": true,
      "name": "ETH",
      "updated": "2026-02-17T19:35:15.116759"
    },
    "CNY=X": {
      "price": 6.90749979019165,
      "change_pct": -0.007240911689454486,
      "prev_close": 6.9079999923706055,
      "name": "USD/CNY",
      "updated": "2026-02-17T19:35:15.186549",
      "unit": "",
      "icon": "🇨🇳",
      "category": "fx"
    },
    "JPY=X": {
      "price": 153.37600708007812,
      "change_pct": 0.3907605723830902,
      "prev_close": 152.7790069580078,
      "name": "USD/JPY",
      "updated": "2026-02-17T19:35:15.266621",
      "unit": "",
      "icon": "🇯🇵",
      "category": "fx"
    },
    "EURUSD=X": {
      "price": 1.1846938133239746,
      "change_pct": -0.17296573402050858,
      "prev_close": 1.1867464780807495,
      "name": "EUR/USD",
      "updated": "2026-02-17T19:35:15.336838",
      "unit": "",
      "icon": "🇪🇺",
      "category": "fx"
    }
  },
  "meta": {
    "total_assets": 11,
    "successful_fetches": 9,
    "failed_fetches": 2
  }
}