{
  "updated_at": "2026-04-16T13:32:40.143112",
  "assets": {
    "GC=F": {
      "price": 4838.7001953125,
      "change_pct": 0.8062540690104166,
      "prev_close": 4800.0,
      "name": "黄金",
      "updated": "2026-04-16T13:32:40.672193",
      "unit": "USD/oz",
      "icon": "🥇",
      "category": "metals"
    },
    "SI=F": {
      "price": 79.66999816894531,
      "change_pct": 0.22518380765068272,
      "prev_close": 79.49099731445312,
      "name": "白银",
      "updated": "2026-04-16T13:32:40.815078",
      "unit": "USD/oz",
      "icon": "🥈",
      "category": "metals"
    },
    "HG=F": {
      "price": 6.0954999923706055,
      "change_pct": 0.3870218307703991,
      "prev_close": 6.072000026702881,
      "name": "铜",
      "updated": "2026-04-16T13:32:41.021752",
      "unit": "USD/吨",
      "icon": "🔶",
      "category": "metals"
    },
    "NICK.L": {
      "price": 15.994999885559082,
      "change_pct": 0.7083279892744136,
      "prev_close": 15.882499694824219,
      "name": "镍",
      "updated": "2026-04-16T13:32:41.212639",
      "unit": "USD (ETC)",
      "icon": "⚙️",
      "category": "metals"
    },
    "REMX": {
      "price": 100.32029724121094,
      "change_pct": 2.9559674955228985,
      "prev_close": 97.44000244140625,
      "name": "稀土ETF",
      "updated": "2026-04-16T13:32:41.399797",
      "unit": "USD",
      "icon": "💎",
      "category": "metals"
    },
    "CL=F": {
      "price": 89.05999755859375,
      "change_pct": -2.442768468144792,
      "prev_close": 91.29000091552734,
      "name": "WTI原油",
      "updated": "2026-04-16T13:32:41.534036",
      "unit": "USD/bbl",
      "icon": "🛢️",
      "category": "commodities"
    },
    "BTCUSDT": {
      "error": true,
      "name": "BTC",
      "updated": "2026-04-16T13:32:41.703536"
    },
    "ETHUSDT": {
      "error": true,
      "name": "ETH",
      "updated": "2026-04-16T13:32:41.804867"
    },
    "CNY=X": {
      "price": 6.820499897003174,
      "change_pct": 0.07042332843765503,
      "prev_close": 6.815700054168701,
      "name": "USD/CNY",
      "updated": "2026-04-16T13:32:42.003880",
      "unit": "",
      "icon": "🇨🇳",
      "category": "fx"
    },
    "JPY=X": {
      "price": 159.05099487304688,
      "change_pct": 0.16309852801968905,
      "prev_close": 158.79200744628906,
      "name": "USD/JPY",
      "updated": "2026-04-16T13:32:42.208101",
      "unit": "",
      "icon": "🇯🇵",
      "category": "fx"
    },
    "EURUSD=X": {
      "price": 1.1782727241516113,
      "change_pct": -0.14138121179681437,
      "prev_close": 1.179940938949585,
      "name": "EUR/USD",
      "updated": "2026-04-16T13:32:42.347963",
      "unit": "",
      "icon": "🇪🇺",
      "category": "fx"
    }
  },
  "meta": {
    "total_assets": 11,
    "successful_fetches": 9,
    "failed_fetches": 2
  }
}