{
  "updated_at": "2026-04-07T19:07:38.577313",
  "assets": {
    "GC=F": {
      "price": 4683.89990234375,
      "change_pct": 0.5819468045195166,
      "prev_close": 4656.7998046875,
      "name": "黄金",
      "updated": "2026-04-07T19:07:38.835203",
      "unit": "USD/oz",
      "icon": "🥇",
      "category": "metals"
    },
    "SI=F": {
      "price": 71.45500183105469,
      "change_pct": -1.6597641514337256,
      "prev_close": 72.66100311279297,
      "name": "白银",
      "updated": "2026-04-07T19:07:38.923619",
      "unit": "USD/oz",
      "icon": "🥈",
      "category": "metals"
    },
    "HG=F": {
      "price": 5.543000221252441,
      "change_pct": -0.7253458916252927,
      "prev_close": 5.583499908447266,
      "name": "铜",
      "updated": "2026-04-07T19:07:38.995546",
      "unit": "USD/吨",
      "icon": "🔶",
      "category": "metals"
    },
    "NICK.L": {
      "price": 14.864999771118164,
      "change_pct": -0.7345616530846889,
      "prev_close": 14.975000381469727,
      "name": "镍",
      "updated": "2026-04-07T19:07:39.078795",
      "unit": "USD (ETC)",
      "icon": "⚙️",
      "category": "metals"
    },
    "REMX": {
      "price": 88.06500244140625,
      "change_pct": -0.4240162705201722,
      "prev_close": 88.44000244140625,
      "name": "稀土ETF",
      "updated": "2026-04-07T19:07:39.226073",
      "unit": "USD",
      "icon": "💎",
      "category": "metals"
    },
    "CL=F": {
      "price": 115.16999816894531,
      "change_pct": 2.4552926046796877,
      "prev_close": 112.41000366210938,
      "name": "WTI原油",
      "updated": "2026-04-07T19:07:39.302210",
      "unit": "USD/bbl",
      "icon": "🛢️",
      "category": "commodities"
    },
    "BTCUSDT": {
      "error": true,
      "name": "BTC",
      "updated": "2026-04-07T19:07:39.426012"
    },
    "ETHUSDT": {
      "error": true,
      "name": "ETH",
      "updated": "2026-04-07T19:07:39.489611"
    },
    "CNY=X": {
      "price": 6.856200218200684,
      "change_pct": -0.38067850634904127,
      "prev_close": 6.882400035858154,
      "name": "USD/CNY",
      "updated": "2026-04-07T19:07:39.567683",
      "unit": "",
      "icon": "🇨🇳",
      "category": "fx"
    },
    "JPY=X": {
      "price": 159.85299682617188,
      "change_pct": 0.04568659871867427,
      "prev_close": 159.77999877929688,
      "name": "USD/JPY",
      "updated": "2026-04-07T19:07:39.636649",
      "unit": "",
      "icon": "🇯🇵",
      "category": "fx"
    },
    "EURUSD=X": {
      "price": 1.1578094959259033,
      "change_pct": 0.5916448867123032,
      "prev_close": 1.150999665260315,
      "name": "EUR/USD",
      "updated": "2026-04-07T19:07:39.744260",
      "unit": "",
      "icon": "🇪🇺",
      "category": "fx"
    }
  },
  "meta": {
    "total_assets": 11,
    "successful_fetches": 9,
    "failed_fetches": 2
  }
}