{
  "updated_at": "2026-02-19T17:35:53.844424",
  "assets": {
    "GC=F": {
      "price": 5019.0,
      "change_pct": 0.6517597513285872,
      "prev_close": 4986.5,
      "name": "黄金",
      "updated": "2026-02-19T17:35:54.397515",
      "unit": "USD/oz",
      "icon": "🥇",
      "category": "metals"
    },
    "SI=F": {
      "price": 77.91000366210938,
      "change_pct": 0.5173605164155657,
      "prev_close": 77.50900268554688,
      "name": "白银",
      "updated": "2026-02-19T17:35:54.465575",
      "unit": "USD/oz",
      "icon": "🥈",
      "category": "metals"
    },
    "HG=F": {
      "price": 5.749000072479248,
      "change_pct": -0.7681000176956917,
      "prev_close": 5.793499946594238,
      "name": "铜",
      "updated": "2026-02-19T17:35:54.625895",
      "unit": "USD/吨",
      "icon": "🔶",
      "category": "metals"
    },
    "NICK.L": {
      "price": 15.175000190734863,
      "change_pct": -0.4918020279681096,
      "prev_close": 15.25,
      "name": "镍",
      "updated": "2026-02-19T17:35:54.698096",
      "unit": "USD (ETC)",
      "icon": "⚙️",
      "category": "metals"
    },
    "REMX": {
      "price": 89.48619842529297,
      "change_pct": -2.147401408947741,
      "prev_close": 91.44999694824219,
      "name": "稀土ETF",
      "updated": "2026-02-19T17:35:54.867759",
      "unit": "USD",
      "icon": "💎",
      "category": "metals"
    },
    "CL=F": {
      "price": 66.52999877929688,
      "change_pct": 2.055524294687723,
      "prev_close": 65.19000244140625,
      "name": "WTI原油",
      "updated": "2026-02-19T17:35:54.933492",
      "unit": "USD/bbl",
      "icon": "🛢️",
      "category": "commodities"
    },
    "BTCUSDT": {
      "error": true,
      "name": "BTC",
      "updated": "2026-02-19T17:35:55.166059"
    },
    "ETHUSDT": {
      "error": true,
      "name": "ETH",
      "updated": "2026-02-19T17:35:55.283270"
    },
    "CNY=X": {
      "price": 6.9079999923706055,
      "change_pct": 0.0,
      "prev_close": 6.9079999923706055,
      "name": "USD/CNY",
      "updated": "2026-02-19T17:35:55.361778",
      "unit": "",
      "icon": "🇨🇳",
      "category": "fx"
    },
    "JPY=X": {
      "price": 154.9739990234375,
      "change_pct": 1.1916479529824975,
      "prev_close": 153.1490020751953,
      "name": "USD/JPY",
      "updated": "2026-02-19T17:35:55.593781",
      "unit": "",
      "icon": "🇯🇵",
      "category": "fx"
    },
    "EURUSD=X": {
      "price": 1.176747441291809,
      "change_pct": -0.7119353807573364,
      "prev_close": 1.185185194015503,
      "name": "EUR/USD",
      "updated": "2026-02-19T17:35:55.915932",
      "unit": "",
      "icon": "🇪🇺",
      "category": "fx"
    }
  },
  "meta": {
    "total_assets": 11,
    "successful_fetches": 9,
    "failed_fetches": 2
  }
}