{
  "updated_at": "2026-04-15T17:23:43.653763",
  "assets": {
    "GC=F": {
      "price": 4821.89990234375,
      "change_pct": -0.064250728626943,
      "prev_close": 4825.0,
      "name": "黄金",
      "updated": "2026-04-15T17:23:44.460952",
      "unit": "USD/oz",
      "icon": "🥇",
      "category": "metals"
    },
    "SI=F": {
      "price": 79.25,
      "change_pct": -0.17760053707801612,
      "prev_close": 79.39099884033203,
      "name": "白银",
      "updated": "2026-04-15T17:23:44.762460",
      "unit": "USD/oz",
      "icon": "🥈",
      "category": "metals"
    },
    "HG=F": {
      "price": 6.08650016784668,
      "change_pct": 0.26357418853436965,
      "prev_close": 6.070499897003174,
      "name": "铜",
      "updated": "2026-04-15T17:23:44.986906",
      "unit": "USD/吨",
      "icon": "🔶",
      "category": "metals"
    },
    "NICK.L": {
      "price": 15.882499694824219,
      "change_pct": -0.2512165973654331,
      "prev_close": 15.922499656677246,
      "name": "镍",
      "updated": "2026-04-15T17:23:45.333653",
      "unit": "USD (ETC)",
      "icon": "⚙️",
      "category": "metals"
    },
    "REMX": {
      "price": 96.98999786376953,
      "change_pct": -1.8319890000813905,
      "prev_close": 98.80000305175781,
      "name": "稀土ETF",
      "updated": "2026-04-15T17:23:45.709954",
      "unit": "USD",
      "icon": "💎",
      "category": "metals"
    },
    "CL=F": {
      "price": 91.93000030517578,
      "change_pct": 0.7120963349819112,
      "prev_close": 91.27999877929688,
      "name": "WTI原油",
      "updated": "2026-04-15T17:23:45.922763",
      "unit": "USD/bbl",
      "icon": "🛢️",
      "category": "commodities"
    },
    "BTCUSDT": {
      "error": true,
      "name": "BTC",
      "updated": "2026-04-15T17:23:46.117464"
    },
    "ETHUSDT": {
      "error": true,
      "name": "ETH",
      "updated": "2026-04-15T17:23:46.238840"
    },
    "CNY=X": {
      "price": 6.817500114440918,
      "change_pct": -0.1873964556567543,
      "prev_close": 6.8302998542785645,
      "name": "USD/CNY",
      "updated": "2026-04-15T17:23:46.475774",
      "unit": "",
      "icon": "🇨🇳",
      "category": "fx"
    },
    "JPY=X": {
      "price": 158.9709930419922,
      "change_pct": -0.1526319718841289,
      "prev_close": 159.21400451660156,
      "name": "USD/JPY",
      "updated": "2026-04-15T17:23:46.783793",
      "unit": "",
      "icon": "🇯🇵",
      "category": "fx"
    },
    "EURUSD=X": {
      "price": 1.18035888671875,
      "change_pct": 0.29509437134810207,
      "prev_close": 1.176885962486267,
      "name": "EUR/USD",
      "updated": "2026-04-15T17:23:47.068844",
      "unit": "",
      "icon": "🇪🇺",
      "category": "fx"
    }
  },
  "meta": {
    "total_assets": 11,
    "successful_fetches": 9,
    "failed_fetches": 2
  }
}