{
  "updated_at": "2026-04-06T12:53:46.023264",
  "assets": {
    "GC=F": {
      "price": 4700.89990234375,
      "change_pct": 1.062020903875094,
      "prev_close": 4651.5,
      "name": "黄金",
      "updated": "2026-04-06T12:53:46.247034",
      "unit": "USD/oz",
      "icon": "🥇",
      "category": "metals"
    },
    "SI=F": {
      "price": 73.5199966430664,
      "change_pct": 1.0792548650960263,
      "prev_close": 72.73500061035156,
      "name": "白银",
      "updated": "2026-04-06T12:53:46.416008",
      "unit": "USD/oz",
      "icon": "🥈",
      "category": "metals"
    },
    "HG=F": {
      "price": 5.6539998054504395,
      "change_pct": 1.6358008262491346,
      "prev_close": 5.563000202178955,
      "name": "铜",
      "updated": "2026-04-06T12:53:46.512816",
      "unit": "USD/吨",
      "icon": "🔶",
      "category": "metals"
    },
    "NICK.L": {
      "price": 14.975000381469727,
      "change_pct": -0.8278145486234312,
      "prev_close": 15.100000381469727,
      "name": "镍",
      "updated": "2026-04-06T12:53:46.598594",
      "unit": "USD (ETC)",
      "icon": "⚙️",
      "category": "metals"
    },
    "REMX": {
      "price": 88.9000015258789,
      "change_pct": 0.4179405305363655,
      "prev_close": 88.52999877929688,
      "name": "稀土ETF",
      "updated": "2026-04-06T12:53:46.888481",
      "unit": "USD",
      "icon": "💎",
      "category": "metals"
    },
    "CL=F": {
      "price": 110.55999755859375,
      "change_pct": -0.8786115733276534,
      "prev_close": 111.54000091552734,
      "name": "WTI原油",
      "updated": "2026-04-06T12:53:47.033503",
      "unit": "USD/bbl",
      "icon": "🛢️",
      "category": "commodities"
    },
    "BTCUSDT": {
      "error": true,
      "name": "BTC",
      "updated": "2026-04-06T12:53:47.283122"
    },
    "ETHUSDT": {
      "error": true,
      "name": "ETH",
      "updated": "2026-04-06T12:53:47.378367"
    },
    "CNY=X": {
      "price": 6.881899833679199,
      "change_pct": -0.046477962859322056,
      "prev_close": 6.8850998878479,
      "name": "USD/CNY",
      "updated": "2026-04-06T12:53:47.707810",
      "unit": "",
      "icon": "🇨🇳",
      "category": "fx"
    },
    "JPY=X": {
      "price": 159.3990020751953,
      "change_pct": -0.05768052166382426,
      "prev_close": 159.49099731445312,
      "name": "USD/JPY",
      "updated": "2026-04-06T12:53:47.862218",
      "unit": "",
      "icon": "🇯🇵",
      "category": "fx"
    },
    "EURUSD=X": {
      "price": 1.1555349826812744,
      "change_pct": 0.11785886661518237,
      "prev_close": 1.1541746854782104,
      "name": "EUR/USD",
      "updated": "2026-04-06T12:53:48.109505",
      "unit": "",
      "icon": "🇪🇺",
      "category": "fx"
    }
  },
  "meta": {
    "total_assets": 11,
    "successful_fetches": 9,
    "failed_fetches": 2
  }
}