{
  "updated_at": "2026-04-29T20:08:32.670932",
  "assets": {
    "GC=F": {
      "price": 4559.10009765625,
      "change_pct": -0.7056496209027551,
      "prev_close": 4591.5,
      "name": "黄金",
      "updated": "2026-04-29T20:08:33.049938",
      "unit": "USD/oz",
      "icon": "🥇",
      "category": "metals"
    },
    "SI=F": {
      "price": 72.08999633789062,
      "change_pct": -1.523127471176512,
      "prev_close": 73.20500183105469,
      "name": "白银",
      "updated": "2026-04-29T20:08:33.219111",
      "unit": "USD/oz",
      "icon": "🥈",
      "category": "metals"
    },
    "HG=F": {
      "price": 5.929500102996826,
      "change_pct": 0.253611731943114,
      "prev_close": 5.9145002365112305,
      "name": "铜",
      "updated": "2026-04-29T20:08:33.355104",
      "unit": "USD/吨",
      "icon": "🔶",
      "category": "metals"
    },
    "NICK.L": {
      "price": 16.860000610351562,
      "change_pct": -1.0998679764595316,
      "prev_close": 17.047500610351562,
      "name": "镍",
      "updated": "2026-04-29T20:08:33.601183",
      "unit": "USD (ETC)",
      "icon": "⚙️",
      "category": "metals"
    },
    "REMX": {
      "price": 100.91500091552734,
      "change_pct": 3.0691422132801796,
      "prev_close": 97.91000366210938,
      "name": "稀土ETF",
      "updated": "2026-04-29T20:08:33.757956",
      "unit": "USD",
      "icon": "💎",
      "category": "metals"
    },
    "CL=F": {
      "price": 107.7699966430664,
      "change_pct": 7.845488155657056,
      "prev_close": 99.93000030517578,
      "name": "WTI原油",
      "updated": "2026-04-29T20:08:33.833056",
      "unit": "USD/bbl",
      "icon": "🛢️",
      "category": "commodities"
    },
    "BTCUSDT": {
      "error": true,
      "name": "BTC",
      "updated": "2026-04-29T20:08:34.017071"
    },
    "ETHUSDT": {
      "error": true,
      "name": "ETH",
      "updated": "2026-04-29T20:08:34.044081"
    },
    "CNY=X": {
      "price": 6.836999893188477,
      "change_pct": 0.2081217887417427,
      "prev_close": 6.822800159454346,
      "name": "USD/CNY",
      "updated": "2026-04-29T20:08:34.128165",
      "unit": "",
      "icon": "🇨🇳",
      "category": "fx"
    },
    "JPY=X": {
      "price": 160.4040069580078,
      "change_pct": 0.6570231394861169,
      "prev_close": 159.35699462890625,
      "name": "USD/JPY",
      "updated": "2026-04-29T20:08:34.303739",
      "unit": "",
      "icon": "🇯🇵",
      "category": "fx"
    },
    "EURUSD=X": {
      "price": 1.1679514646530151,
      "change_pct": -0.3749101237630482,
      "prev_close": 1.1723467111587524,
      "name": "EUR/USD",
      "updated": "2026-04-29T20:08:34.442192",
      "unit": "",
      "icon": "🇪🇺",
      "category": "fx"
    }
  },
  "meta": {
    "total_assets": 11,
    "successful_fetches": 9,
    "failed_fetches": 2
  }
}