{
  "updated_at": "2026-02-25T16:18:59.464403",
  "assets": {
    "GC=F": {
      "price": 5212.2001953125,
      "change_pct": 1.0939212685046933,
      "prev_close": 5155.7998046875,
      "name": "黄金",
      "updated": "2026-02-25T16:18:59.706800",
      "unit": "USD/oz",
      "icon": "🥇",
      "category": "metals"
    },
    "SI=F": {
      "price": 91.04000091552734,
      "change_pct": 4.096870637112057,
      "prev_close": 87.45700073242188,
      "name": "白银",
      "updated": "2026-02-25T16:18:59.786832",
      "unit": "USD/oz",
      "icon": "🥈",
      "category": "metals"
    },
    "HG=F": {
      "price": 6.0254998207092285,
      "change_pct": 1.7305413522805866,
      "prev_close": 5.922999858856201,
      "name": "铜",
      "updated": "2026-02-25T16:18:59.870050",
      "unit": "USD/吨",
      "icon": "🔶",
      "category": "metals"
    },
    "NICK.L": {
      "price": 15.859999656677246,
      "change_pct": 0.8585009343885428,
      "prev_close": 15.725000381469727,
      "name": "镍",
      "updated": "2026-02-25T16:18:59.956104",
      "unit": "USD (ETC)",
      "icon": "⚙️",
      "category": "metals"
    },
    "REMX": {
      "price": 99.97000122070312,
      "change_pct": 5.576088967326951,
      "prev_close": 94.69000244140625,
      "name": "稀土ETF",
      "updated": "2026-02-25T16:19:00.082411",
      "unit": "USD",
      "icon": "💎",
      "category": "metals"
    },
    "CL=F": {
      "price": 65.33999633789062,
      "change_pct": -0.44187250901071873,
      "prev_close": 65.62999725341797,
      "name": "WTI原油",
      "updated": "2026-02-25T16:19:00.200103",
      "unit": "USD/bbl",
      "icon": "🛢️",
      "category": "commodities"
    },
    "BTCUSDT": {
      "error": true,
      "name": "BTC",
      "updated": "2026-02-25T16:19:00.426880"
    },
    "ETHUSDT": {
      "error": true,
      "name": "ETH",
      "updated": "2026-02-25T16:19:00.546820"
    },
    "CNY=X": {
      "price": 6.86870002746582,
      "change_pct": -0.5689051092673592,
      "prev_close": 6.9079999923706055,
      "name": "USD/CNY",
      "updated": "2026-02-25T16:19:00.674131",
      "unit": "",
      "icon": "🇨🇳",
      "category": "fx"
    },
    "JPY=X": {
      "price": 154.63499450683594,
      "change_pct": 0.19177912359965796,
      "prev_close": 154.33900451660156,
      "name": "USD/JPY",
      "updated": "2026-02-25T16:19:00.780878",
      "unit": "",
      "icon": "🇯🇵",
      "category": "fx"
    },
    "EURUSD=X": {
      "price": 1.1809163093566895,
      "change_pct": 0.12989476916564419,
      "prev_close": 1.1793843507766724,
      "name": "EUR/USD",
      "updated": "2026-02-25T16:19:00.902799",
      "unit": "",
      "icon": "🇪🇺",
      "category": "fx"
    }
  },
  "meta": {
    "total_assets": 11,
    "successful_fetches": 9,
    "failed_fetches": 2
  }
}